{
	"name": "One Dark Code",
	"colors": {
		// Base colors
		"focusBorder": "#ffffff00",
		"foreground": "#abb2bf",
		"disabledForeground": "#5c6370",
		"widget.border": "#2c313c",
		"widget.shadow": "#ffffff00",
		"selection.background": "#61afef50",
		"descriptionForeground": "#abb2bf",
		"errorForeground": "#c24038",
		"icon.foreground": "#abb2bf",
		"sash.hoverBorder": "#5c6370",

		// Window border
		"window.activeBorder": "#2c313c",
		"window.inactiveBorder": "#2c313c",

		// Text colors
		"textBlockQuote.background": "#2c313c",
		"textBlockQuote.border": "#5c6370",
		"textCodeBlock.background": "#2c313c",
		"textLink.foreground": "#61afef",
		"textLink.activeForeground": "#61afef",
		"textPreformat.foreground": "#d19a66",
		"textSeparator.foreground": "#5c6370",

		// Action colors
		"toolbar.activeBackground": "#404754",
		"toolbar.hoverBackground": "#404754",
		"toolbar.hoverOutline": "#ffffff00",

		// Button control
		"button.background": "#323842",
		"button.foreground": "#e6e6e6",
		"button.border": "#ffffff00",
		"button.separator": "#ffffff00",
		"button.hoverBackground": "#404754",
		"button.secondaryBackground": "#404754",
		"button.secondaryForeground": "#e6e6e6",
		"button.secondaryHoverBackground": "#5c6370",
		"checkbox.background": "#323842",
		"checkbox.foreground": "#98c379",
		"checkbox.border": "#404754",

		// Dropdown control
		"dropdown.background": "#323842",
		"dropdown.foreground": "#abb2bf",
		"dropdown.listBackground": "#21252b",
		"dropdown.border": "#30363f",

		// Input control
		"input.background": "#323842",
		"input.foreground": "#abb2bf",
		"input.border": "#ffffff00",
		"input.placeholderForeground": "#5c6370",
		"inputOption.activeBackground": "#404754",
		"inputOption.activeBorder": "#ffffff00",
		"inputOption.activeForeground": "#98c379",
		"inputOption.hoverBackground": "#2c313c",
		"inputValidation.errorBackground": "#21252b",
		"inputValidation.errorForeground": "#abb2bf",
		"inputValidation.errorBorder": "#c24038",
		"inputValidation.infoBackground": "#21252b",
		"inputValidation.infoForeground": "#abb2bf",
		"inputValidation.infoBorder": "#61afef",
		"inputValidation.warningBackground": "#21252b",
		"inputValidation.warningForeground": "#abb2bf",
		"inputValidation.warningBorder": "#d19a66",

		// Scrollbar control
		"scrollbar.shadow": "#ffffff00",
		"scrollbarSlider.background": "#40475480",
		"scrollbarSlider.activeBackground": "#5c637080",
		"scrollbarSlider.hoverBackground": "#5c637080",

		// Badge
		"badge.background": "#404754",
		"badge.foreground": "#abb2bf",

		// Lists and trees
		"list.activeSelectionBackground": "#323842",
		"list.activeSelectionForeground": "#e6e6e6",
		"list.activeSelectionIconForeground": "#e6e6e6",
		"list.dropBackground": "#2c313a",
		"list.focusBackground": "#2c313a",
		"list.focusForeground": "#abb2bf",
		"list.focusOutline": "#ffffff00",
		"list.focusAndSelectionOutline": "#ffffff00",
		"list.highlightForeground": "#e6e6e6",
		"list.hoverBackground": "#323842",
		"list.hoverForeground": "#abb2bf",
		"list.inactiveSelectionBackground": "#323842",
		"list.inactiveSelectionForeground": "#e6e6e6",
		"list.inactiveSelectionIconForeground": "#e6e6e6",
		"list.inactiveFocusBackground": "#2c313a",
		"list.inactiveFocusOutline": "#ffffff00",
		"list.errorForeground": "#e45454",
		"list.warningForeground": "#d19a66",
		"tree.indentGuidesStroke": "#5c6370",
		"tree.inactiveIndentGuidesStroke": "#404754",

		// List Filter
		"listFilterWidget.background": "#21252b",
		"listFilterWidget.shadow": "#ffffff00",
		"list.filterMatchBackground": "#61afef15",
		"list.filterMatchBorder": "#5c6370",

		// Activity Bar
		"activityBar.background": "#21252b",
		"activityBar.dropBorder": "#5c6370",
		"activityBar.foreground": "#abb2bf",
		"activityBarBadge.background": "#98c379",
		"activityBarBadge.foreground": "#000000",

		// Profiles
		"profileBadge.background": "#98c379",
		"profileBadge.foreground": "#000000",

		// Side Bar
		"sideBar.background": "#282c34",
		"sideBar.foreground": "#abb2bf",
		"sideBar.dropBackground": "#40475480",
		"sideBarTitle.foreground": "#e6e6e6",
		"sideBarSectionHeader.background": "#ffffff00",
		"sideBarSectionHeader.foreground": "#e6e6e6",
		"sideBarSectionHeader.border": "#ffffff00",

		// Minimap
		"minimap.findMatchHighlight": "#61afef15",
		"minimap.selectionHighlight": "#61afef50",
		"minimap.errorHighlight": "#c24038",
		"minimap.warningHighlight": "#d19a66",
		"minimap.infoHighlight": "#61afef",
		"minimap.selectionOccurrenceHighlight": "#61afef15",
		"minimapSlider.background": "#40475480",
		"minimapSlider.activeBackground": "#5c637080",
		"minimapSlider.hoverBackground": "#5c637080",
		"minimapGutter.addedBackground": "#ffffff00",
		"minimapGutter.deletedBackground": "#ffffff00",
		"minimapGutter.modifiedBackground": "#ffffff00",

		// Editor Groups & Tabs
		"editorGroup.border": "#2c313c",
		"editorGroup.dropBackground": "#40475480",
		"editorGroupHeader.border": "#282c34",
		"editorGroupHeader.tabsBackground": "#282c34",
		"editorGroup.dropIntoPromptForeground": "#abb2bf",
		"editorGroup.dropIntoPromptBackground": "#2c313c",
		"editorGroup.dropIntoPromptBorder": "#5c6370",
		"tab.activeBackground": "#282c34",
		"tab.activeForeground": "#e6e6e6",
		"tab.border": "#ffffff00",
		"tab.activeBorder": "#282c34",
		"tab.hoverBackground": "#323842",
		"tab.unfocusedHoverBackground": "#323842",
		"tab.lastPinnedBorder": "#ffffff00",
		"tab.inactiveBackground": "#282c34",
		"tab.inactiveForeground": "#abb2bf",
		"tab.unfocusedInactiveForeground": "#5c6370",
		"tab.unfocusedActiveForeground": "#abb2bf",

		// Editor colors
		"editor.background": "#282c34",
		"editor.foreground": "#abb2bf",
		"editorLineNumber.activeForeground": "#abb2bf",
		"editorLineNumber.foreground": "#5c6370",
		"editorLineNumber.dimmedForeground": "#404754",
		"editorCursor.background": "#e6e6e6",
		"editorCursor.foreground": "#528bff",

		// Selection
		"editor.selectionBackground": "#67769660",
		"editor.inactiveSelectionBackground": "#67769630",
		"editor.selectionHighlightBackground": "#67769630",
		"editor.selectionHighlightBorder": "#ffffff00",
		"editor.wordHighlightBackground": "#67769630",
		"editor.wordHighlightStrongBackground": "#67769630",
		"editor.wordHighlightStrongBorder": "#5c6370",
		"editor.wordHighlightTextBackground": "#67769630",
		"editor.wordHighlightTextBorder": "#5c6370",
		"editor.findMatchBackground": "#61afef15",
		"editor.findMatchBorder": "#61afef",
		"editor.findMatchHighlightBackground": "#61afef15",
		"editor.findMatchHighlightBorder": "#5c6370",
		"editor.lineHighlightBackground": "#2c313c",
		"editorUnicodeHighlight.background": "#d19a6615",
		"editorUnicodeHighlight.border": "#ffffff00",
		"editorBracketMatch.background": "#61afef15",
		"editorBracketMatch.border": "#5c6370",

		// Editor Indent Guide
		"editorIndentGuide.background1": "#404754",
		"editorIndentGuide.background2": "#404754",
		"editorIndentGuide.background3": "#404754",
		"editorIndentGuide.background4": "#404754",
		"editorIndentGuide.background5": "#404754",
		"editorIndentGuide.background6": "#404754",
		"editorIndentGuide.activeBackground1": "#5c6370",
		"editorIndentGuide.activeBackground2": "#5c6370",
		"editorIndentGuide.activeBackground3": "#5c6370",
		"editorIndentGuide.activeBackground4": "#5c6370",
		"editorIndentGuide.activeBackground5": "#5c6370",
		"editorIndentGuide.activeBackground6": "#5c6370",

		// Brackets
		"editorBracketHighlight.foreground1": "#d19a66",
		"editorBracketHighlight.foreground2": "#c678dd",
		"editorBracketHighlight.foreground3": "#56b6c2",
		"editorBracketHighlight.foreground4": "#d19a66",
		"editorBracketHighlight.foreground5": "#c678dd",
		"editorBracketHighlight.foreground6": "#56b6c2",
		"editorBracketPairGuide.background1": "#404754",
		"editorBracketPairGuide.background2": "#404754",
		"editorBracketPairGuide.background3": "#404754",
		"editorBracketPairGuide.background4": "#404754",
		"editorBracketPairGuide.background5": "#404754",
		"editorBracketPairGuide.background6": "#404754",
		"editorBracketPairGuide.activeBackground1": "#5c6370",
		"editorBracketPairGuide.activeBackground2": "#5c6370",
		"editorBracketPairGuide.activeBackground3": "#5c6370",
		"editorBracketPairGuide.activeBackground4": "#5c6370",
		"editorBracketPairGuide.activeBackground5": "#5c6370",
		"editorBracketPairGuide.activeBackground6": "#5c6370",

		// Inlay Hints
		"editorInlayHint.background": "#ffffff00",
		"editorInlayHint.foreground": "#5c6370",

		// Misc
		"editorRuler.foreground": "#abb2bf10",
		"editor.linkedEditingBackground": "#e06c7530",
		"editorCodeLens.foreground": "#7f848e",
		"editor.foldBackground": "#61afef15",
		"editor.foldPlaceholderForeground": "#7f848e",
		"editorWhitespace.foreground": "#ffffff10",
		"editorLightBulb.foreground": "#e5c07b",

		// Sticky Scroll
		"editorStickyScroll.background": "#282c34",
		"editorStickyScrollHover.background": "#282c34",

		// Overview Ruler
		"editorOverviewRuler.border": "#ffffff00",
		"editorOverviewRuler.findMatchForeground": "#61afef50",
		"editorOverviewRuler.warningForeground": "#d19a66",
		"editorOverviewRuler.infoForeground": "#61afef",
		"editorOverviewRuler.errorForeground": "#c24038",
		"editorOverviewRuler.addedForeground": "#98c3798c",
		"editorOverviewRuler.deletedForeground": "#e06c758c",
		"editorOverviewRuler.modifiedForeground": "#e5c07b8c",

		// Errors and warnings
		"editorError.foreground": "#c24038",
		"editorWarning.foreground": "#d19a66",
		"editorInfo.foreground": "#61afef",
		"problemsErrorIcon.foreground": "#c24038",
		"problemsWarningIcon.foreground": "#d19a66",
		"problemsInfoIcon.foreground": "#61afef",

		// Editor Gutter
		"editorGutter.addedBackground": "#98c3798c",
		"editorGutter.deletedBackground": "#e06c758c",
		"editorGutter.modifiedBackground": "#e5c07b8c",
		"editorGutter.foldingControlForeground": "#abb2bf",

		// Diff editor colors
		"diffEditor.border": "#2c313c",
		"diffEditor.diagonalFill": "#404754",
		"diffEditor.insertedLineBackground": "#98c37915",
		"diffEditor.insertedTextBackground": "#98c37938",
		"diffEditor.removedLineBackground": "#e06c7515",
		"diffEditor.removedTextBackground": "#e06c7538",
		"diffEditor.unchangedCodeBackground": "#ffffff00",
		"diffEditor.unchangedRegionBackground": "#ffffff00",
		"diffEditor.unchangedRegionForeground": "#abb2bf",
		"diffEditor.unchangedRegionShadow": "#ffffff00",
		"diffEditor.move.border": "#5c6370",
		"diffEditor.moveActive.border": "#5c6370",
		"multiDiffEditor.headerBackground": "#323842",
		"multiDiffEditor.border": "#ffffff00",

		// Merge Editor
		// Note: For some reason the merge editor doesn't use `diffEditor.*LineBackground`
		// settings for the inserted or removed line backgrounds. It is also not possible
		// to change the border between panels with `merge.border` or any other setting.
		"mergeEditor.conflict.handledFocused.border": "#abb2bf",
		"mergeEditor.conflict.handledUnfocused.border": "#ffffff00",
		"mergeEditor.conflict.unhandledFocused.border": "#404754",
		"mergeEditor.conflict.unhandledUnfocused.border": "#ffffff00",

		// Chat
		"chat.requestBorder": "#2c313c",
		"chat.avatarBackground": "#ffffff00",
		"chat.avatarForeground": "#abb2bf",

		// Inline Chat
		"inlineChat.background": "#21252b",
		"inlineChat.border": "#ffffff00",

		// Editor Widgets
		"editorWidget.foreground": "#abb2bf",
		"editorWidget.background": "#21252b",
		"editorWidget.border": "#2c313c",
		"editorWidget.resizeBorder": "#ffffff00",
		"editorHoverWidget.foreground": "#abb2bf",
		"editorHoverWidget.background": "#21252b",
		"editorHoverWidget.border": "#2c313c",
		"editorHoverWidget.statusBarBackground": "#21252b",
		"editorSuggestWidget.foreground": "#abb2bf",
		"editorSuggestWidget.background": "#21252b",
		"editorSuggestWidget.border": "#2c313c",
		"editorSuggestWidget.selectedBackground": "#323842",
		"editorSuggestWidget.selectedForeground": "#e6e6e6",
		"editorSuggestWidget.selectedIconForeground": "#e6e6e6",

		// Editor marker view
		"editorMarkerNavigation.background": "#21252b",
		"editorMarkerNavigationError.headerBackground": "#21252b",
		"editorMarkerNavigationError.background": "#c24038",
		"editorMarkerNavigationWarning.headerBackground": "#21252b",
		"editorMarkerNavigationWarning.background": "#d19a66",
		"editorMarkerNavigationInfo.headerBackground": "#21252b",
		"editorMarkerNavigationInfo.background": "#61afef",

		// Peek View
		"peekView.border": "#2c313c",
		"peekViewEditor.background": "#21252b",
		"peekViewResult.background": "#21252b",
		"peekViewResult.fileForeground": "#e6e6e6",
		"peekViewResult.lineForeground": "#abb2bf",
		"peekViewResult.selectionBackground": "#2c313a",
		"peekViewResult.selectionForeground": "#e6e6e6",
		"peekViewTitle.background": "#21252b",
		"peekViewTitleDescription.foreground": "#abb2bf",
		"peekViewTitleLabel.foreground": "#e6e6e6",
		"peekViewEditor.matchHighlightBackground": "#61afef15",
		"peekViewEditor.matchHighlightBorder": "#5c6370",
		"peekViewResult.matchHighlightBackground": "#61afef15",

		// Panel colors
		"panel.background": "#282c34",
		"panel.border": "#282c34",
		"panel.dropBorder": "#5c6370",

		// Status Bar colors
		"statusBar.background": "#282c34",
		"statusBar.foreground": "#abb2bf",
		"statusBarItem.hoverBackground": "#2c313c",
		"statusBarItem.hoverForeground": "#abb2bf",
		"statusBar.border": "#282c34",
		"statusBar.debuggingBackground": "#21252b",
		"statusBar.debuggingBorder": "#2c313c",
		"statusBar.debuggingForeground": "#abb2bf",
		"statusBar.noFolderBackground": "#21252b",
		"statusBar.noFolderForeground": "#abb2bf",
		"statusBar.noFolderBorder": "#2c313c",
		"statusBarItem.remoteBackground": "#ffffff00",
		"statusBarItem.remoteForeground": "#98c379",
		"statusBarItem.errorBackground": "#c24038",
		"statusBarItem.errorForeground": "#e6e6e6",
		"statusBarItem.errorHoverBackground": "#e45454",
		"statusBarItem.errorHoverForeground": "#e6e6e6",
		"statusBarItem.warningBackground": "#d19a66",
		"statusBarItem.warningForeground": "#e6e6e6",
		"statusBarItem.warningHoverBackground": "#e5c07b",
		"statusBarItem.warningHoverForeground": "#e6e6e6",

		// Title Bar colors
		"titleBar.activeBackground": "#282c34",
		"titleBar.activeForeground": "#abb2bf",
		"titleBar.inactiveBackground": "#282c34",
		"titleBar.inactiveForeground": "#abb2bf",

		// Menu Bar colors
		"menubar.selectionForeground": "#e6e6e6",
		"menubar.selectionBackground": "#323842",
		"menu.foreground": "#abb2bf",
		"menu.background": "#21252b",
		"menu.selectionForeground": "#e6e6e6",
		"menu.selectionBackground": "#323842",
		"menu.separatorBackground": "#2c313c",
		"menu.border": "#2c313c",

		// Command Center colors
		"commandCenter.foreground": "#abb2bf",
		"commandCenter.background": "#282c34",
		"commandCenter.border": "#2c313c",
		"commandCenter.activeForeground": "#abb2bf",
		"commandCenter.activeBackground": "#282c34",
		"commandCenter.activeBorder": "#2c313c",
		"commandCenter.inactiveBorder": "#2c313c",
		"commandCenter.inactiveForeground": "#abb2bf",
		"commandCenter.debuggingBackground": "#ffffff00",

		// Notification colors
		"notificationCenter.border": "#2c313c",
		"notificationCenterHeader.background": "#21252b",
		"notificationCenterHeader.foreground": "#e6e6e6",
		"notifications.foreground": "#abb2bf",
		"notifications.background": "#21252b",
		"notifications.border": "#2c313c",
		"notificationLink.foreground": "#61afef",
		"notificationsErrorIcon.foreground": "#c24038",
		"notificationsWarningIcon.foreground": "#d19a66",
		"notificationsInfoIcon.foreground": "#61afef",

		// Extension color
		"extensionIcon.starForeground": "#98c379fd",
		"extensionIcon.verifiedForeground": "#61afeffd",

		// Keybinding label colors
		"keybindingLabel.background": "#404754",
		"keybindingLabel.foreground": "#abb2bf",
		"keybindingTable.headerBackground": "#404754",
		"keybindingTable.rowsBackground": "#2c313c",

		// Terminal
		"terminal.background": "#282c34",
		"terminal.foreground": "#abb2bf",
		"terminal.border": "#282c34",
		"terminal.selectionBackground": "#abb2bf30",
		"terminalCommandDecoration.errorBackground": "#c24038",
		"terminalCommandDecoration.successBackground": "#98c379",

		// Terminal Colors
		"terminal.ansiBlack": "#21252b",
		"terminal.ansiBlue": "#61afef",
		"terminal.ansiCyan": "#56b6c2",
		"terminal.ansiGreen": "#98c379",
		"terminal.ansiMagenta": "#c678dd",
		"terminal.ansiRed": "#e06c75",
		"terminal.ansiWhite": "#abb2bf",
		"terminal.ansiYellow": "#e5c07b",
		"terminal.ansiBrightBlack": "#5c6370",
		"terminal.ansiBrightBlue": "#61afef",
		"terminal.ansiBrightCyan": "#56b6c2",
		"terminal.ansiBrightGreen": "#98c379",
		"terminal.ansiBrightMagenta": "#c678dd",
		"terminal.ansiBrightRed": "#e06c75",
		"terminal.ansiBrightWhite": "#e6e6e6",
		"terminal.ansiBrightYellow": "#e5c07b",

		// Debug colors
		"debugToolBar.background": "#21252b",
		"debugConsole.infoForeground": "#abb2bf",
		"editor.stackFrameHighlightBackground": "#e06c754d",
		"debugTokenExpression.name": "#c678dd",
		"debugTokenExpression.boolean": "#d19a66",
		"debugTokenExpression.number": "#d19a66",
		"debugTokenExpression.string": "#98c379",
		"debugTokenExpression.value": "#abb2bf",
		"debugTokenExpression.error": "#c24038",

		// Testing colors
		"testing.iconErrored": "#c24038",
		"testing.iconFailed": "#c24038",
		"testing.iconPassed": "#98c379",
		"testing.iconQueued": "#abb2bf",
		"testing.iconSkipped": "#61afef",
		"testing.iconUnset": "#5c6370",
		"testing.runAction": "#98c379",

		// Welcome page colors
		"welcomePage.progress.foreground": "#61afef",
		"welcomePage.tileBorder": "#2c313c",
		"welcomePage.tileHoverBackground": "#404754",
		"walkthrough.stepTitle.foreground": "#e6e6e6",

		// Git colors
		"gitDecoration.addedResourceForeground": "#98c379",
		"gitDecoration.modifiedResourceForeground": "#e5c07b",
		"gitDecoration.deletedResourceForeground": "#e06c75",
		"gitDecoration.ignoredResourceForeground": "#5c6370",
		"gitDecoration.untrackedResourceForeground": "#98c379",
		"gitDecoration.conflictingResourceForeground": "#d19a66",

		// Settings Editor colors
		"settings.headerForeground": "#e6e6e6",
		"settings.modifiedItemIndicator": "#e5c07b",
		"settings.rowHoverBackground": "#2c313c",
		"settings.focusedRowBackground": "#ffffff00",
		"settings.settingsHeaderHoverForeground": "#e6e6e6",
		"settings.headerBorder": "#ffffff00",
		"settings.sashBorder": "#ffffff00",

		// Breadcrumbs colors
		"breadcrumb.background": "#21252b",
		"breadcrumb.foreground": "#abb2bf",
		"breadcrumb.focusForeground": "#e6e6e6",
		"breadcrumb.activeSelectionForeground": "#e6e6e6",

		// Icons colors
		"symbolIcon.booleanForeground": "#d19a66",
		"symbolIcon.classForeground": "#e5c07b",
		"symbolIcon.constantForeground": "#e06c75",
		"symbolIcon.constructorForeground": "#c678dd",
		"symbolIcon.enumeratorForeground": "#e5c07b",
		"symbolIcon.enumeratorMemberForeground": "#e5c07b",
		"symbolIcon.functionForeground": "#61afef",
		"symbolIcon.interfaceForeground": "#61afef",
		"symbolIcon.methodForeground": "#61afef",
		"symbolIcon.stringForeground": "#98c379",
		"symbolIcon.structForeground": "#e5c07b",

		// Debug Icons
		"debugIcon.breakpointForeground": "#d19a66",
		"debugIcon.breakpointDisabledForeground": "#5c6370",
		"debugIcon.breakpointCurrentStackframeForeground": "#d19a66",
		"debugIcon.startForeground": "#98c379",
		"debugIcon.continueForeground": "#61afef",
		"debugIcon.pauseForeground": "#61afef",
		"debugIcon.stopForeground": "#e06c75",
		"debugIcon.restartForeground": "#98c379",
		"debugIcon.stepIntoForeground": "#61afef",
		"debugIcon.stepBackForeground": "#61afef",
		"debugIcon.stepOutForeground": "#61afef",
		"debugIcon.stepOverForeground": "#61afef",

		// Error Lens Extension
		"errorLens.errorBackground": "#e06c7515",
		"errorLens.errorForeground": "#e45454",
		"errorLens.warningBackground": "#d19a6615",
		"errorLens.warningForeground": "#d19a66",
		"errorLens.infoBackground": "#61afef15",
		"errorLens.infoForeground": "#61afef",
		"errorLens.hintBackground": "#98c37915",
		"errorLens.hintForeground": "#98c379"
	},
	"tokenColors": [
		// =============================================================================
		// Invalid
		// =============================================================================
		{
			"name": "Invalid",
			"scope": ["invalid", "invalid.illegal"],
			"settings": {
				"foreground": "#e45454"
			}
		},
		{
			"scope": ["invalid.deprecated"],
			"settings": {
				"fontStyle": "strikethrough"
			}
		},
		// =============================================================================
		// Comments
		// =============================================================================
		{
			"name": "Comment",
			"scope": [
				"comment",
				"punctuation.definition.comment",
				"unused.comment",
				"wildcard.comment"
			],
			"settings": {
				"foreground": "#7f848e",
				"fontStyle": "italic"
			}
		},
		{
			"name": "JSDoc-style keywords",
			"scope": [
				"comment keyword.codetag.notation",
				"comment.block.documentation keyword",
				"comment.block.documentation storage.type.class"
			],
			"settings": {
				"foreground": "#c678dd"
			}
		},
		{
			"name": "JSDoc-style types",
			"scope": ["comment.block.documentation entity.name.type"],
			"settings": {
				"foreground": "#e5c07b"
			}
		},
		{
			"name": "JSDoc-style comment parameters",
			"scope": ["comment.block.documentation variable"],
			"settings": {
				"foreground": "#d19a66"
			}
		},
		// =============================================================================
		// Classes/Namespaces
		// =============================================================================
		{
			"name": "Classes",
			"scope": [
				"entity.name.type.class",
				"entity.name.class",
				"support.class"
			],
			"settings": {
				"foreground": "#e5c07b"
			}
		},
		{
			"name": "Namespace",
			"scope": ["entity.name.namespace"],
			"settings": {
				"foreground": "#e5c07b"
			}
		},
		{
			"name": "this, super, self, etc.",
			"scope": [
				"keyword.expressions-and-types.swift",
				"keyword.other.this",
				"variable.language",
				"variable.language punctuation.definition.variable.php", // the "$" symbol in $this
				"variable.other.readwrite.instance.ruby", // ruby's "@" instance symbol
				"variable.parameter.function.language.special" // Special words as parameters
			],
			"settings": {
				"foreground": "#d19a66",
				"fontStyle": "italic"
			}
		},
		// =============================================================================
		// Constants
		// =============================================================================
		{
			"name": "Constants",
			"scope": ["constant", "support.constant"],
			"settings": {
				"foreground": "#d19a66"
			}
		},
		{
			"name": "Contants - Escape Character",
			"scope": [
				"constant.character.escape",
				"constant.character.string.escape",
				"constant.regexp"
			],
			"settings": {
				"foreground": "#56b6c2"
			}
		},
		// =============================================================================
		// Variables
		// =============================================================================
		{
			"name": "Variables",
			"scope": ["variable", "entity.name.variable"],
			"settings": {
				"foreground": "#e06c75"
			}
		},
		{
			"name": "Destructuring / aliasing variable name",
			"scope": ["meta.import variable.other.readwrite"],
			"settings": {
				"foreground": "#e06c75"
			}
		},
		// =============================================================================
		// Functions/Methos
		// =============================================================================
		{
			"name": "Functions",
			"scope": [
				"entity.name.function",
				"support.function",
				"keyword.operator.function",
				"meta.function-call.generic.python"
			],
			"settings": {
				"foreground": "#61afef"
			}
		},
		{
			"name": "Function Parameters",
			"scope": [
				"variable.parameter",
				"entity.name.variable.parameter",
				"meta.function.definition variable.parameter",
				"meta.function.definition variable.language",
				"meta.function.definition variable.other",
				"meta.at-rule.function variable", // Sass function params
				"meta.at-rule.mixin variable" // Sass mixin params
			],
			"settings": {
				"foreground": "#d19a66",
				"fontStyle": "italic"
			}
		},
		{
			"name": "Decorators",
			"scope": [
				"meta.decorator variable.other.readwrite",
				"meta.decorator variable.other.property",
				"punctuation.decorator"
			],
			"settings": {
				"foreground": "#56b6c2",
				"fontStyle": "italic"
			}
		},
		{
			"name": "Attributes",
			"scope": ["meta.attribute", "meta.attribute punctuation"],
			"settings": {
				"foreground": "#abb2bf"
			}
		},
		{
			"name": "Macros",
			"scope": ["entity.name.function.macro"],
			"settings": {
				"foreground": "#56b6c2"
			}
		},
		// =============================================================================
		// Keywords
		// =============================================================================
		{
			"name": "Keyword",
			"scope": [
				"keyword",
				"keyword.control punctuation",
				"punctuation.definition.keyword",
				"keyword.operator.new",
				"keyword.operator.expression"
			],
			"settings": {
				"foreground": "#c678dd"
			}
		},
		{
			"name": "Keyword - Operators",
			"scope": ["keyword.operator"],
			"settings": {
				"foreground": "#56b6c2"
			}
		},
		{
			"name": "Keyword - Reset",
			"scope": [
				"keyword.operator.type.annotation",
				"keyword.operator.namespace",
				"keyword.operator.key-value",
				"keyword.operator.access.dot"
			],
			"settings": {
				"foreground": "#abb2bf"
			}
		},
		{
			"name": "Keyword - Units",
			"scope": ["keyword.other.unit"],
			"settings": {
				"foreground": "#e06c75"
			}
		},
		// =============================================================================
		// Storage
		// =============================================================================
		{
			"name": "Storage",
			"scope": ["storage"],
			"settings": {
				"foreground": "#c678dd"
			}
		},
		// =============================================================================
		// Types
		// =============================================================================
		{
			"name": "Types",
			"scope": [
				"support.type",
				"entity.name.type",
				"storage.type.java",
				"storage.type.generic.java"
			],
			"settings": {
				"foreground": "#e5c07b"
			}
		},
		// =============================================================================
		// Punctuation
		// =============================================================================
		{
			"name": "Punctuation",
			"scope": [
				"punctuation",
				"string.template meta.brace.square",
				"string.template punctuation.accessor",
				"meta.brace"
			],
			"settings": {
				"foreground": "#abb2bf"
			}
		},
		// =============================================================================
		// Strings
		// =============================================================================
		{
			"name": "Strings",
			"scope": [
				"string",
				"punctuation.definition.string",
				"meta.attribute-selector"
			],
			"settings": {
				"foreground": "#98c379"
			}
		},
		{
			"name": "String interpolation",
			"scope": [
				"punctuation.definition.template-expression.begin",
				"punctuation.definition.template-expression.end",
				"punctuation.definition.interpolation",
				"punctuation.section.embedded",
				"meta.interpolation"
			],
			"settings": {
				"foreground": "#c678dd"
			}
		},
		// =============================================================================
		// Entities
		// =============================================================================
		{
			"name": "HTML Tags",
			"scope": ["entity.name.tag"],
			"settings": {
				"foreground": "#e06c75"
			}
		},
		// =============================================================================
		// Attributes
		// =============================================================================
		{
			"name": "Attributes",
			"scope": ["entity.other.attribute-name"],
			"settings": {
				"foreground": "#d19a66",
				"fontStyle": "italic"
			}
		},
		// =============================================================================
		// Properties/Keys/Fields
		// =============================================================================
		{
			"name": "Properties",
			"scope": [
				"variable.other.property",
				"variable.other.object.property",
				"entity.name.variable.property"
			],
			"settings": {
				"foreground": "#abb2bf"
			}
		},
		{
			"name": "Keys",
			"scope": [
				"support.type.property-name",
				"support.type.property-name punctuation",
				"meta.object-literal.key",
				"meta.object-literal.key entity.name.function"
			],
			"settings": {
				"foreground": "#e06c75"
			}
		},
		{
			"name": "Fields",
			"scope": ["entity.name.variable.field"],
			"settings": {
				"foreground": "#abb2bf"
			}
		},
		// =============================================================================
		// CSS
		// =============================================================================
		{
			"name": "CSS - Property Names",
			"scope": [
				"support.type.property-name.css",
				"support.type.vendored.property-name"
			],
			"settings": {
				"foreground": "#abb2bf"
			}
		},
		{
			"name": "CSS - Classes",
			"scope": [
				"entity.other.attribute-name.class",
				"entity.other.attribute-name.class punctuation"
			],
			"settings": {
				"foreground": "#d19a66"
			}
		},
		{
			"name": "CSS - IDs",
			"scope": [
				"entity.other.attribute-name.id",
				"entity.other.attribute-name.id punctuation"
			],
			"settings": {
				"foreground": "#56b6c2"
			}
		},
		{
			"name": "CSS - Pseudo Classes",
			"scope": [
				"entity.other.attribute-name.pseudo-class",
				"entity.other.attribute-name.pseudo-element",
				"entity.other.attribute-name.pseudo-class punctuation"
			],
			"settings": {
				"foreground": "#c678dd"
			}
		},
		{
			"name": "CSS - Header",
			"scope": ["meta.at-rule.header"],
			"settings": {
				"foreground": "#e06c75"
			}
		},
		{
			"name": "CSS - Tailwind @apply",
			"scope": [
				"meta.at-rule.apply.tailwind entity.other.attribute-name.class"
			],
			"settings": {
				"foreground": "#98c379"
			}
		},
		{
			"name": "CSS - Variables",
			"scope": [
				"bem.support.modifier.scss",
				"variable.parameter.url.scss"
			],
			"settings": {
				"foreground": "#e06c75"
			}
		},
		// =============================================================================
		// Diffs
		// =============================================================================
		{
			"name": "Inserted",
			"scope": ["markup.inserted"],
			"settings": {
				"foreground": "#98c379"
			}
		},
		{
			"name": "Deleted",
			"scope": ["markup.deleted"],
			"settings": {
				"foreground": "#e06c75"
			}
		},
		{
			"name": "Changed",
			"scope": ["markup.changed"],
			"settings": {
				"foreground": "#e5c07b"
			}
		},
		// =============================================================================
		// RegEx
		// =============================================================================
		{
			"name": "RegExp",
			"scope": [
				"string.regexp",
				"constant.other.character-class.set.regexp",
				"constant.character.escape.backslash.regexp"
			],
			"settings": {
				"foreground": "#98c379"
			}
		},
		// =============================================================================
		// Edge Cases
		// =============================================================================
		{
			"name": "Java Import",
			"scope": ["storage.modifier.import"],
			"settings": {
				"foreground": "#e5c07b"
			}
		},
		{
			"name": "Rust Import",
			"scope": ["meta.use.rust keyword.operator"],
			"settings": {
				"foreground": "#d19a66"
			}
		},
		{
			"name": "Rust Trait Bounds",
			"scope": ["meta.function.definition.rust keyword.operator.math"],
			"settings": {
				"foreground": "#abb2bf"
			}
		},
		{
			"name": "Rust Interpolation Variables",
			"scope": ["meta.interpolation.rust"],
			"settings": {
				"foreground": "#e06c75"
			}
		},
		{
			"name": "C# - Base Class",
			"scope": ["variable.language.base"],
			"settings": {
				"foreground": "#c678dd"
			}
		},
		{
			"name": "Log - Error",
			"scope": ["log.error", "log.exceptiontype"],
			"settings": {
				"foreground": "#e45454"
			}
		},
		{
			"name": "Log - Warning",
			"scope": ["log.warning"],
			"settings": {
				"foreground": "#d19a66"
			}
		},
		{
			"name": "Log - Info",
			"scope": ["log.info"],
			"settings": {
				"foreground": "#61afef"
			}
		},
		{
			"name": "Log - Constant",
			"scope": ["log.constant"],
			"settings": {
				"foreground": "#abb2bf"
			}
		},
		{
			"name": "ES6 String in HTML",
			"scope": [
				"source.js entity.name.tag",
				"source.ts entity.name.tag",
				"source.jsx entity.name.tag",
				"source.tsx entity.name.tag"
			],
			"settings": {
				"foreground": "#c678dd"
			}
		},
		{
			"name": "ES6 String in HTML",
			"scope": [
				"entity.name.tag.html",
				"entity.name.tag.jsx",
				"entity.name.tag.tsx",
				"entity.name.tag.xml",
				"entity.name.tag.localname.xml"
			],
			"settings": {
				"foreground": "#e06c75"
			}
		},
		// =============================================================================
		// Markup
		// =============================================================================
		{
			"scope": ["emphasis"],
			"settings": {
				"fontStyle": "italic"
			}
		},
		{
			"scope": ["strong"],
			"settings": {
				"fontStyle": "bold"
			}
		},
		{
			"name": "URL",
			"scope": ["*url*", "*link*", "*uri*"],
			"settings": {
				"fontStyle": "underline"
			}
		},
		{
			"name": "Markup - Italic",
			"scope": ["markup.italic", "punctuation.definition.italic"],
			"settings": {
				"foreground": "#d19a66",
				"fontStyle": "italic"
			}
		},
		{
			"name": "Markup - Bold",
			"scope": ["markup.bold", "punctuation.definition.bold"],
			"settings": {
				"foreground": "#d19a66",
				"fontStyle": "bold"
			}
		},
		{
			"name": "Markup - Bold-Italic",
			"scope": [
				"markup.bold markup.italic",
				"markup.bold punctuation.definition.italic"
			],
			"settings": {
				"fontStyle": "bold italic"
			}
		},
		{
			"name": "Markup - Underline",
			"scope": ["markup.underline"],
			"settings": {
				"fontStyle": "underline"
			}
		},
		{
			"name": "Markdown - Heading",
			"scope": [
				"markdown.heading",
				"markup.heading | markup.heading entity.name",
				"markup.heading.markdown punctuation.definition.heading.markdown",
				"entity.name.section.markdown"
			],
			"settings": {
				"foreground": "#e06c75"
			}
		},
		{
			"name": "Markdown - Link",
			"scope": ["meta.link.inline.markdown", "markup.underline.link"],
			"settings": {
				"foreground": "#61afef"
			}
		},
		{
			"name": "Markdown - Link Title",
			"scope": ["string.other.link.title.markdown"],
			"settings": {
				"foreground": "#c678dd"
			}
		},
		{
			"name": "Markdown - Link Description",
			"scope": ["string.other.link.description.title.markdown"],
			"settings": {
				"foreground": "#98c379"
			}
		},
		{
			"name": "Markdown - Link Anchor",
			"scope": ["constant.other.reference.link.markdown"],
			"settings": {
				"foreground": "#d19a66"
			}
		},
		{
			"name": "Markup - Code",
			"scope": [
				"fenced_code.block.language",
				"markup.raw.inner.restructuredtext",
				"markup.fenced_code.block.markdown punctuation.definition.markdown",
				"markup.inline.raw",
				"markup.raw.restructuredtext"
			],
			"settings": {
				"foreground": "#98c379"
			}
		},
		{
			"name": "Markup - Quote",
			"scope": ["markup.quote.markdown", "punctuation.definition.quote"],
			"settings": {
				"foreground": "#7f848e"
			}
		},
		{
			"name": "Markup - Lists",
			"scope": ["punctuation.definition.list"],
			"settings": {
				"foreground": "#e5c07b"
			}
		},
		{
			"name": "Markup - Punctuation",
			"scope": [
				"punctuation.definition.metadata.markdown",
				"punctuation.definition.link.title.end.markdown",
				"punctuation.definition.link.title.begin.markdown"
			],
			"settings": {
				"foreground": "#abb2bf"
			}
		},
		// =============================================================================
		// Markup - Math
		// =============================================================================
		{
			"name": "Markup - Math",
			"scope": [
				"markup.math",
				"markup.math constant.numeric",
				"markup.math punctuation"
			],
			"settings": {
				"foreground": "#56b6c2"
			}
		},
		{
			"name": "Markup - Math Constant",
			"scope": [
				"markup.math punctuation.definition.constant",
				"markup.math constant.character"
			],
			"settings": {
				"foreground": "#98c379"
			}
		},
		{
			"name": "Markup - Math Punctuation",
			"scope": ["markup.math punctuation.definition"],
			"settings": {
				"foreground": "#d19a66"
			}
		},
		{
			"name": "Markup - Math Function",
			"scope": [
				"markup.math entity.name.function",
				"markup.math punctuation.definition.function"
			],
			"settings": {
				"foreground": "#61afef"
			}
		},
		{
			"name": "Markup - Math Delimiter",
			"scope": ["punctuation.definition.math"],
			"settings": {
				"foreground": "#c678dd"
			}
		}
	],
	"semanticHighlighting": true,
	"semanticTokenColors": {
		"namespace": {
			"foreground": "#e5c07b"
		},
		"type": {
			"foreground": "#e5c07b"
		},
		"struct": {
			"foreground": "#e5c07b"
		},
		"class": {
			"foreground": "#e5c07b"
		},
		"interface": {
			"foreground": "#e5c07b"
		},
		"enum": {
			"foreground": "#e5c07b"
		},
		"function": {
			"foreground": "#61afef"
		},
		"method": {
			"foreground": "#61afef"
		},
		"macro": {
			"foreground": "#56b6c2"
		},
		"parameter": {
			"foreground": "#e06c75",
			"fontStyle": "italic"
		},
		"parameter.declaration": {
			"foreground": "#d19a66",
			"fontStyle": "italic"
		},
		"property": {
			"foreground": "#abb2bf"
		},
		"property.declaration": {
			"foreground": "#e06c75"
		},
		"enumMember": {
			"foreground": "#d19a66"
		},
		"decorator": {
			"foreground": "#abb2bf"
		},
		"selfTypeKeyword": {
			"foreground": "#e5c07b"
		},
		"selfKeyword": {
			"foreground": "#e06c75"
		},
		"selfKeyword.declaration": {
			"foreground": "#d19a66",
			"fontStyle": "italic"
		},
		"punctuation.injected": {
			"foreground": "#abb2bf"
		},
		"builtinType": {
			"foreground": "#e5c07b"
		},
		"*.mutable": {
			"underline": false
		},
		"*.attribute": {
			"foreground": "#abb2bf"
		},
		"string.attribute": {
			"foreground": "#98c379"
		},
		"boolean.attribute": {
			"foreground": "#d19a66"
		},
		"number.attribute": {
			"foreground": "#d19a66"
		},
		"derive": {
			"foreground": "#e5c07b"
		},
		"*.documentation.injected": {
			"foreground": "#7f848e",
			"fontStyle": "italic bold"
		},
		"xmlDocCommentName": {
			"foreground": "#e06c75"
		},
		"xmlDocCommentAttributeName": {
			"foreground": "#d19a66"
		},
		"xmlDocCommentAttributeQuotes": {
			"foreground": "#98c379"
		}
	}
}
